Workbook

Sheet Atletas
A1: Nome do Jogador | B1: Clube Atual | C1: Clube Real | D1: Nacionalidade | E1: Idade | F1: Data de Nascimento | G1: Início do contrato | H1: Final do contrato | I1: Salário | J1: Empresário | K1: Posição | L1: Lesões no ano | M1: Dias sem jogar por lesão | N1: Valor de Mercado Nacional | O1: Valor de Mercado Internacional | P1: Pé Dominante | Q1: Ganho por Fornecedor | R1: Fornecedor | S1: Altura | T1: Data de hoje | U1: Dias para o final de contrato | V1: Contrato | W1: Gasto semestral | X1: Gasto anual (Com 13 salario)
A2: Mycael Pontes Moreira | B2: Athletico Paranaense | C2: Athletico Paranaense | D2: Brasil | E2: =DATEDIF(F2,TODAY(),"Y") -> 22 | F2: 38058 | G2: 44927 | H2: 46477 | I2: 185000 | J2: Master Talents | K2: Goleiro | L2: 0 | M2: 0 | N2: 3000000 | O2: =N2*3.5 -> 10500000 | P2: Esquerdo | Q2: =IF(E2>30,100000,IF(E2>24,120000,IF(E2>16,160000))) -> 160000 | R2: Nike | S2: 1.91 | T2: =TODAY() -> 46296 | U2: =_xlfn.DAYS(H2,T2) -> 181 | V2: =IF(U2<180, "Pre contrato","Com Contrato em vigor") -> Com Contrato em vigor | W2: =I2*6 -> 1110000 | X2: =I2*13 -> 2405000
A3: Leonardo Matias Baiersdorf Linck | B3: Athletico Paranaense | C3: Athletico Paranaense | D3: Brasil | E3: =DATEDIF(F3,TODAY(),"Y") -> 25 | F3: 36953 | G3: 44927 | H3: 46387 | I3: 116000 | J3: R13 Fussball | K3: Goleiro | L3: 0 | M3: 0 | N3: 1000000 | O3: =N3*3.5 -> 3500000 | P3: Direito | Q3: =IF(E3>30,100000,IF(E3>24,120000,IF(E3>16,160000))) -> 120000 | R3: Nike | S3: 1.94 | T3: =TODAY() -> 46296 | U3: =_xlfn.DAYS(H3,T3) -> 91 | V3: =IF(U3<180, "Pre contrato","Com Contrato em vigor") -> Pre contrato | W3: =I3*6 -> 696000 | X3: =I3*13 -> 1508000
A4: Matheus Soares Rocha | B4: Athletico Paranaense | C4: Athletico Paranaense | D4: Brasil | E4: =DATEDIF(F4,TODAY(),"Y") -> 21 | F4: 38362 | G4: 45478 | H4: 45657 | I4: 73000 | J4: F3 Sports | K4: Goleiro | L4: 0 | M4: 0 | N4: 90000 | O4: =N4*3.5 -> 315000 | P4: Esquerdo | Q4: =IF(E4>30,100000,IF(E4>24,120000,IF(E4>16,160000))) -> 160000 | R4: Adidas | S4: 1.9 | T4: =TODAY() -> 46296 | U4: =_xlfn.DAYS(H4,T4) -> -639 | V4: =IF(U4<180, "Pre contrato","Com Contrato em vigor") -> Pre contrato | W4: =I4*6 -> 438000 | X4: =I4*13 -> 949000
A5: Kaique Rocha Lima | B5: Athletico Paranaense | C5: Athletico Paranaense | D5: Brasil | E5: =DATEDIF(F5,TODAY(),"Y") -> 25 | F5: 36950 | G5: 44946 | H5: 46387 | I5: 120000 | J5: BBM Sports | K5: Zagueiro | L5: 0 | M5: 0 | N5: 1000000 | O5: =N5*3.5 -> 3500000 | P5: Direito | Q5: =IF(E5>30,100000,IF(E5>24,120000,IF(E5>16,160000))) -> 120000 | R5: Puma | S5: 1.95 | T5: =TODAY() -> 46296 | U5: =_xlfn.DAYS(H5,T5) -> 91 | V5: =IF(U5<180, "Pre contrato","Com Contrato em vigor") -> Pre contrato | W5: =I5*6 -> 720000 | X5: =I5*13 -> 1560000
A6: Mateo Gamarra González | B6: Athletico Paranaense | C6: Athletico Paranaense | D6: Paraguai | E6: =DATEDIF(F6,TODAY(),"Y") -> 25 | F6: 36819 | G6: 45292 | H6: 46752 | I6: 220000 | J6: EagleEye | K6: Zagueiro | L6: 1 | M6: 12 | N6: 3000000 | O6: =N6*3.5 -> 10500000 | P6: Esquerdo | Q6: =IF(E6>30,100000,IF(E6>24,120000,IF(E6>16,160000))) -> 120000 | R6: Adidas | S6: 1.83 | T6: =TODAY() -> 46296 | U6: =_xlfn.DAYS(H6,T6) -> 456 | V6: =IF(U6<180, "Pre contrato","Com Contrato em vigor") -> Com Contrato em vigor | W6: =I6*6 -> 1320000 | X6: =I6*13 -> 2860000
A7: Luan Patrick Wiedthauper | B7: Athletico Paranaense | C7: Athletico Paranaense | D7: Brasil | E7: =DATEDIF(F7,TODAY(),"Y") -> 24 | F7: 37276 | G7: 44587 | H7: 45657 | I7: 140000 | J7: UJ Football Talent | K7: Zagueiro | L7: 1 | M7: 90 | N7: 780000 | O7: =N7*3.5 -> 2730000 | P7: Direito | Q7: =IF(E7>30,100000,IF(E7>24,120000,IF(E7>16,160000))) -> 160000 | R7: Nike | S7: 1.9 | T7: =TODAY() -> 46296 | U7: =_xlfn.DAYS(H7,T7) -> -639 | V7: =IF(U7<180, "Pre contrato","Com Contrato em vigor") -> Pre contrato | W7: =I7*6 -> 840000 | X7: =I7*13 -> 1820000
A8: Lucas Belezi Barbosa | B8: Athletico Paranaense | C8: Athletico Paranaense | D8: Brasil | E8: =DATEDIF(F8,TODAY(),"Y") -> 23 | F8: 37749 | G8: 45292 | H8: 46022 | I8: 150000 | J8: FJB Sports | K8: Zagueiro | L8: 2 | M8: 53 | N8: 1240000 | O8: =N8*3.5 -> 4340000 | P8: Direito | Q8: =IF(E8>30,100000,IF(E8>24,120000,IF(E8>16,160000))) -> 160000 | R8: Adidas | S8: 1.86 | T8: =TODAY() -> 46296 | U8: =_xlfn.DAYS(H8,T8) -> -274 | V8: =IF(U8<180, "Pre contrato","Com Contrato em vigor") -> Pre contrato | W8: =I8*6 -> 900000 | X8: =I8*13 -> 1950000
A9: Thiago Heleno Henrique Ferreira | B9: Athletico Paranaense | C9: Athletico Paranaense | D9: Brasil | E9: =DATEDIF(F9,TODAY(),"Y") -> 38 | F9: 32403 | G9: 42755 | H9: 46022 | I9: 450000 | J9: More than Sport GmbH | K9: Zagueiro | L9: 3 | M9: 41 | N9: 650000 | O9: =N9*3.5 -> 2275000 | P9: Esquerdo | Q9: =IF(E9>30,100000,IF(E9>24,120000,IF(E9>16,160000))) -> 100000 | R9: Nike | S9: 1.87 | T9: =TODAY() -> 46296 | U9: =_xlfn.DAYS(H9,T9) -> -274 | V9: =IF(U9<180, "Pre contrato","Com Contrato em vigor") -> Pre contrato | W9: =I9*6 -> 2700000 | X9: =I9*13 -> 5850000
A10: Marcos Victor Ferreira da Silva | B10: Athletico Paranaense | C10: EC Bahia | D10: Brasil | E10: =DATEDIF(F10,TODAY(),"Y") -> 24 | F10: 37251 | G10: 45538 | H10: 46752 | I10: 160000 | J10: LINK SPORTS | K10: Zagueiro | L10: 0 | M10: 0 | N10: 600000 | O10: =N10*3.5 -> 2100000 | P10: Direito | Q10: =IF(E10>30,100000,IF(E10>24,120000,IF(E10>16,160000))) -> 160000 | R10: Puma | S10: 1.84 | T10: =TODAY() -> 46296 | U10: =_xlfn.DAYS(H10,T10) -> 456 | V10: =IF(U10<180, "Pre contrato","Com Contrato em vigor") -> Com Contrato em vigor | W10: =I10*6 -> 960000 | X10: =I10*13 -> 2080000
A11: Lucas Ángel Esquivel | B11: Athletico Paranaense | C11: Athletico Paranaense | D11: Argentina | E11: =DATEDIF(F11,TODAY(),"Y") -> 24 | F11: 37178 | G11: 45110 | H11: 46934 | I11: 310000 | J11: Universal Twenty Two | K11: Lateral Esquerdo | L11: 2 | M11: 21 | N11: 2300000 | O11: =N11*3.5 -> 8050000 | P11: Esquerdo | Q11: =IF(E11>30,100000,IF(E11>24,120000,IF(E11>16,160000))) -> 160000 | R11: Puma | S11: 1.83 | T11: =TODAY() -> 46296 | U11: =_xlfn.DAYS(H11,T11) -> 638 | V11: =IF(U11<180, "Pre contrato","Com Contrato em vigor") -> Com Contrato em vigor | W11: =I11*6 -> 1860000 | X11: =I11*13 -> 4030000
A12: Fernando Augusto Pereira Bueno Júnior | B12: Athletico Paranaense | C12: Athletico Paranaense | D12: Brasil | E12: =DATEDIF(F12,TODAY(),"Y") -> 27 | F12: 36417 | G12: 44942 | H12: 46387 | I12: 230000 | J12: Elenko Sports Ltda | K12: Lateral Esquerdo | L12: 4 | M12: 35 | N12: 867000 | O12: =N12*3.5 -> 3034500 | P12: Esquerdo | Q12: =IF(E12>30,100000,IF(E12>24,120000,IF(E12>16,160000))) -> 120000 | R12: Nike | S12: 1.81 | T12: =TODAY() -> 46296 | U12: =_xlfn.DAYS(H12,T12) -> 91 | V12: =IF(U12<180, "Pre contrato","Com Contrato em vigor") -> Pre contrato | W12: =I12*6 -> 1380000 | X12: =I12*13 -> 2990000
A13: Leonardo Ezequiel Godoy | B13: Athletico Paranaense | C13: Athletico Paranaense | D13: Argentina | E13: =DATEDIF(F13,TODAY(),"Y") -> 31 | F13: 34817 | G13: 45302 | H13: 46752 | I13: 410000 | J13: FC3 Sports | K13: Lateral Direito | L13: 2 | M13: 16 | N13: 4000000 | O13: =N13*3.5 -> 14000000 | P13: Direito | Q13: =IF(E13>30,100000,IF(E13>24,120000,IF(E13>16,160000))) -> 100000 | R13: Mizuno | S13: 1.73 | T13: =TODAY() -> 46296 | U13: =_xlfn.DAYS(H13,T13) -> 456 | V13: =IF(U13<180, "Pre contrato","Com Contrato em vigor") -> Com Contrato em vigor | W13: =I13*6 -> 2460000 | X13: =I13*13 -> 5330000
... A128: Francisco Dyogo Bento Alves | B128: CR Flamengo | C128: CR Flamengo | D128: Brasil | E128: =DATEDIF(F128,TODAY(),"Y") -> 22 | F128: 37995 | G128: 44950 | H128: 46022 | I128: 200000 | J128: LINK SPORTS | K128: Goleiro | L128: 0 | M128: 0 | N128: 1500000 | O128: =N128*3.5 -> 5250000 | P128: Direito | Q128: =IF(E128>30,100000,IF(E128>24,120000,IF(E128>16,160000))) -> 160000 | R128: Nike | S128: 1.8 | T128: =TODAY() -> 46296 | U128: =_xlfn.DAYS(H128,T128) -> -274 | V128: =IF(U128<180, "Pre contrato","Com Contrato em vigor") -> Pre contrato | W128: =I128*6 -> 1200000 | X128: =I128*13 -> 2600000
A129: Leonardo Rech Ortiz | B129: CR Flamengo | C129: CR Flamengo | D129: Brasil | E129: =DATEDIF(F129,TODAY(),"Y") -> 30 | F129: 35067 | G129: 45357 | H129: 47118 | I129: 900000 | J129: Talents Sports | K129: Zagueiro | L129: 0 | M129: 0 | N129: 26000000 | O129: =N129*3.5 -> 91000000 | P129: Direito | Q129: =IF(E129>30,100000,IF(E129>24,120000,IF(E129>16,160000))) -> 120000 | R129: Puma | S129: 1.85 | T129: =TODAY() -> 46296 | U129: =_xlfn.DAYS(H128,T128) -> -274 | V129: =IF(U129<180, "Pre contrato","Com Contrato em vigor") -> Pre contrato | W129: =I129*6 -> 5400000 | X129: =I129*13 -> 11700000
A130: Leonardo Pereira | B130: CR Flamengo | C130: CR Flamengo | D130: Brasil | E130: =DATEDIF(F130,TODAY(),"Y") -> 30 | F130: 35095 | G130: 43861 | H130: 46752 | I130: 600000 | J130: R13 Fussball | K130: Zagueiro | L130: 0 | M130: 0 | N130: 15000000 | O130: =N130*3.5 -> 52500000 | P130: Direito | Q130: =IF(E130>30,100000,IF(E130>24,120000,IF(E130>16,160000))) -> 120000 | R130: Nike | S130: 1.89 | T130: =TODAY() -> 46296 | U130: =_xlfn.DAYS(H130,T130) -> 456 | V130: =IF(U130<180, "Pre contrato","Com Contrato em vigor") -> Com Contrato em vigor | W130: =I130*6 -> 3600000 | X130: =I130*13 -> 7800000
A131: Fabrício Bruno Soares de Faria | B131: CR Flamengo | C131: CR Flamengo | D131: Brasil | E131: =DATEDIF(F131,TODAY(),"Y") -> 30 | F131: 35107 | G131: 44601 | H131: 47118 | I131: 670000 | J131: Sem empresario | K131: Zagueiro | L131: 0 | M131: 0 | N131: 18000000 | O131: =N131*3.5 -> 63000000 | P131: Direito | Q131: =IF(E131>30,100000,IF(E131>24,120000,IF(E131>16,160000))) -> 120000 | R131: Adidas | S131: 1.92 | T131: =TODAY() -> 46296 | U131: =_xlfn.DAYS(H131,T131) -> 822 | V131: =IF(U131<180, "Pre contrato","Com Contrato em vigor") -> Com Contrato em vigor | W131: =I131*6 -> 4020000 | X131: =I131*13 -> 8710000
A132: David Luiz Moreira Marinho | B132: CR Flamengo | C132: CR Flamengo | D132: Brasil | E132: =DATEDIF(F132,TODAY(),"Y") -> 39 | F132: 31889 | G132: 44601 | H132: 47118 | I132: 600000 | J132: Bertolucci Sports | K132: Zagueiro | L132: 1 | M132: 14 | N132: 3000000 | O132: =N132*3.5 -> 10500000 | P132: Direito | Q132: =IF(E132>30,100000,IF(E132>24,120000,IF(E132>16,160000))) -> 100000 | R132: Adidas | S132: 1.89 | T132: =TODAY() -> 46296 | U132: =_xlfn.DAYS(H132,T132) -> 822 | V132: =IF(U132<180, "Pre contrato","Com Contrato em vigor") -> Com Contrato em vigor | W132: =I132*6 -> 3600000 | X132: =I132*13 -> 7800000
A133: Ayrton Lucas Dantas de Medeiros | B133: CR Flamengo | C133: CR Flamengo | D133: Brasil | E133: =DATEDIF(F133,TODAY(),"Y") -> 29 | F133: 35600 | G133: 44927 | H133: 46752 | I133: 500000 | J133: Carlos Leite | K133: Lateral Esquerdo | L133: 0 | M133: 0 | N133: 10000000 | O133: =N133*3.5 -> 35000000 | P133: Esquerdo | Q133: =IF(E133>30,100000,IF(E133>24,120000,IF(E133>16,160000))) -> 120000 | R133: Adidas | S133: 1.8 | T133: =TODAY() -> 46296 | U133: =_xlfn.DAYS(H132,T132) -> 822 | V133: =IF(U133<180, "Pre contrato","Com Contrato em vigor") -> Com Contrato em vigor | W133: =I133*6 -> 3000000 | X133: =I133*13 -> 6500000
A134: Matías Nicolás Viña Susperreguy | B134: CR Flamengo | C134: CR Flamengo | D134: Uruguai | E134: =DATEDIF(F134,TODAY(),"Y") -> 28 | F134: 35743 | G134: 45316 | H134: 47118 | I134: 650000 | J134: Sem empresario | K134: Lateral Esquerdo | L134: 2 | M134: 87 | N134: 14000000 | O134: =N134*3.5 -> 49000000 | P134: Esquerdo | Q134: =IF(E134>30,100000,IF(E134>24,120000,IF(E134>16,160000))) -> 120000 | R134: Adidas | S134: 1.75 | T134: =TODAY() -> 46296 | U134: =_xlfn.DAYS(H134,T134) -> 822 | V134: =IF(U134<180, "Pre contrato","Com Contrato em vigor") -> Com Contrato em vigor | W134: =I134*6 -> 3900000 | X134: =I134*13 -> 8450000
A135: Alex Sandro Lobo Silva | B135: CR Flamengo | C135: CR Flamengo | D135: Brasil | E135: =DATEDIF(F135,TODAY(),"Y") -> 35 | F135: 33264 | G135: 45530 | H135: 46387 | I135: 1500000 | J135: Sem empresario | K135: Lateral Esquerdo | L135: 0 | M135: 0 | N135: 10000000 | O135: =N135*3.5 -> 35000000 | P135: Esquerdo | Q135: =IF(E135>30,100000,IF(E135>24,120000,IF(E135>16,160000))) -> 100000 | R135: Puma | S135: 1.8 | T135: =TODAY() -> 46296 | U135: =_xlfn.DAYS(H135,T135) -> 91 | V135: =IF(U135<180, "Pre contrato","Com Contrato em vigor") -> Pre contrato | W135: =I135*6 -> 9000000 | X135: =I135*13 -> 19500000
A136: Guillermo Varela Olivera | B136: CR Flamengo | C136: CR Flamengo | D136: Uruguai | E136: =DATEDIF(F136,TODAY(),"Y") -> 33 | F136: 34052 | G136: 44938 | H136: 46022 | I136: 600000 | J136: Rickman Sports | K136: Lateral Direito | L136: 0 | M136: 0 | N136: 16000000 | O136: =N136*3.5 -> 56000000 | P136: Direito | Q136: =IF(E136>30,100000,IF(E136>24,120000,IF(E136>16,160000))) -> 100000 | R136: Nike | S136: 1.73 | T136: =TODAY() -> 46296 | U136: =_xlfn.DAYS(H136,T136) -> -274 | V136: =IF(U136<180, "Pre contrato","Com Contrato em vigor") -> Pre contrato | W136: =I136*6 -> 3600000 | X136: =I136*13 -> 7800000
A137: Wesley Vinícius França Lima | B137: CR Flamengo | C137: CR Flamengo | D137: Brasil | E137: =DATEDIF(F137,TODAY(),"Y") -> 23 | F137: 37870 | G137: 44927 | H137: 47118 | I137: 400000 | J137: MCL Sports | K137: Lateral Direito | L137: 0 | M137: 0 | N137: 25000000 | O137: =N137*3.5 -> 87500000 | P137: Direito | Q137: =IF(E137>30,100000,IF(E137>24,120000,IF(E137>16,160000))) -> 160000 | R137: Nike | S137: 1.78 | T137: =TODAY() -> 46296 | U137: =_xlfn.DAYS(H136,T136) -> -274 | V137: =IF(U137<180, "Pre contrato","Com Contrato em vigor") -> Pre contrato | W137: =I137*6 -> 2400000 | X137: =I137*13 -> 5200000
A138: Allan Rodrigues de Souza | B138: CR Flamengo | C138: CR Flamengo | D138: Brasil | E138: =DATEDIF(F138,TODAY(),"Y") -> 29 | F138: 35492 | G138: 45108 | H138: 46752 | I138: 560000 | J138: Bertolucci Sports | K138: Volante | L138: 1 | M138: 60 | N138: 7500000 | O138: =N138*3.5 -> 26250000 | P138: Direito | Q138: =IF(E138>30,100000,IF(E138>24,120000,IF(E138>16,160000))) -> 120000 | R138: Nike | S138: 1.72 | T138: =TODAY() -> 46296 | U138: =_xlfn.DAYS(H138,T138) -> 456 | V138: =IF(U138<180, "Pre contrato","Com Contrato em vigor") -> Com Contrato em vigor | W138: =I138*6 -> 3360000 | X138: =I138*13 -> 7280000
A139: Erick Antonio Pulgar Farfán | B139: CR Flamengo | C139: CR Flamengo | D139: Chile | E139: =DATEDIF(F139,TODAY(),"Y") -> 32 | F139: 34349 | G139: 44771 | H139: 46022 | I139: 550000 | J139: Vibra Futbol | K139: Volante | L139: 0 | M139: 0 | N139: 17000000 | O139: =N139*3.5 -> 59500000 | P139: Direito | Q139: =IF(E139>30,100000,IF(E139>24,120000,IF(E139>16,160000))) -> 100000 | R139: Nike | S139: 1.87 | T139: =TODAY() -> 46296 | U139: =_xlfn.DAYS(H139,T139) -> -274 | V139: =IF(U139<180, "Pre contrato","Com Contrato em vigor") -> Pre contrato | W139: =I139*6 -> 3300000 | X139: =I139*13 -> 7150000
A140: Gerson Santos da Silva | B140: CR Flamengo | C140: CR Flamengo | D140: Brasil | E140: =DATEDIF(F140,TODAY(),"Y") -> 29 | F140: 35570 | G140: 44927 | H140: 46752 | I140: 1200000 | J140: Carlos Leite | K140: Meio Campo | L140: 0 | M140: 0 | N140: 24000000 | O140: =N140*3.5 -> 84000000 | P140: Esquerdo | Q140: =IF(E140>30,100000,IF(E140>24,120000,IF(E140>16,160000))) -> 120000 | R140: Nike | S140: 1.84 | T140: =TODAY() -> 46296 | U140: =_xlfn.DAYS(H140,T140) -> 456 | V140: =IF(U140<180, "Pre contrato","Com Contrato em vigor") -> Com Contrato em vigor | W140: =I140*6 -> 7200000 | X140: =I140*13 -> 15600000
A141: Diego Nicolás de la Cruz Arcosa | B141: CR Flamengo | C141: CR Flamengo | D141: Uruguai | E141: =DATEDIF(F141,TODAY(),"Y") -> 29 | F141: 35582 | G141: 45292 | H141: 46934 | I141: 1200000 | J141: Paco Casal | K141: Meio Campo | L141: 2 | M141: 21 | N141: 22000000 | O141: =N141*3.5 -> 77000000 | P141: Esquerdo | Q141: =IF(E141>30,100000,IF(E141>24,120000,IF(E141>16,160000))) -> 120000 | R141: Nike | S141: 1.67 | T141: =TODAY() -> 46296 | U141: =_xlfn.DAYS(H140,T140) -> 456 | V141: =IF(U141<180, "Pre contrato","Com Contrato em vigor") -> Com Contrato em vigor | W141: =I141*6 -> 7200000 | X141: =I141*13 -> 15600000
A142: Carlos Jonás Alcaraz | B142: CR Flamengo | C142: CR Flamengo | D142: Argentina | E142: =DATEDIF(F142,TODAY(),"Y") -> 23 | F142: 37590 | G142: 45532 | H142: 47299 | I142: 1000000 | J142: Rol Sports Management | K142: Meio Campo | L142: 1 | M142: 10 | N142: 30000000 | O142: =N142*3.5 -> 105000000 | P142: Direito | Q142: =IF(E142>30,100000,IF(E142>24,120000,IF(E142>16,160000))) -> 160000 | R142: Nike | S142: 1.83 | T142: =TODAY() -> 46296 | U142: =_xlfn.DAYS(H142,T142) -> 1003 | V142: =IF(U142<180, "Pre contrato","Com Contrato em vigor") -> Com Contrato em vigor | W142: =I142*6 -> 6000000 | X142: =I142*13 -> 13000000
A143: Giorgian Daniel de Arrascaeta Benedetti | B143: CR Flamengo | C143: CR Flamengo | D143: Uruguai | E143: =DATEDIF(F143,TODAY(),"Y") -> 32 | F143: 34486 | G143: 43477 | H143: 46387 | I143: 1600000 | J143: Daniel Fonseca | K143: Meio Campo | L143: 1 | M143: 50 | N143: 13000000 | O143: =N143*3.5 -> 45500000 | P143: Direito | Q143: =IF(E143>30,100000,IF(E143>24,120000,IF(E143>16,160000))) -> 100000 | R143: Nike | S143: 1.74 | T143: =TODAY() -> 46296 | U143: =_xlfn.DAYS(H143,T143) -> 91 | V143: =IF(U143<180, "Pre contrato","Com Contrato em vigor") -> Pre contrato | W143: =I143*6 -> 9600000 | X143: =I143*13 -> 20800000
A144: Lorran Lucas Pereira de Sousa | B144: CR Flamengo | C144: CR Flamengo | D144: Brasil | E144: =DATEDIF(F144,TODAY(),"Y") -> 20 | F144: 38902 | G144: 45292 | H144: 47483 | I144: 150000 | J144: Roc Nation Sports | K144: Meio Campo | L144: 0 | M144: 0 | N144: 14000000 | O144: =N144*3.5 -> 49000000 | P144: Direito | Q144: =IF(E144>30,100000,IF(E144>24,120000,IF(E144>16,160000))) -> 160000 | R144: Nike | S144: 1.8 | T144: =TODAY() -> 46296 | U144: =_xlfn.DAYS(H144,T144) -> 1187 | V144: =IF(U144<180, "Pre contrato","Com Contrato em vigor") -> Com Contrato em vigor | W144: =I144*6 -> 900000 | X144: =I144*13 -> 1950000
A145: Everton Sousa Soares | B145: CR Flamengo | C145: CR Flamengo | D145: Brasil | E145: =DATEDIF(F145,TODAY(),"Y") -> 30 | F145: 35146 | G145: 44760 | H145: 46203 | I145: 1500000 | J145: Bertolucci Sports | K145: Atacante | L145: 1 | M145: 45 | N145: 16000000 | O145: =N145*3.5 -> 56000000 | P145: Direito | Q145: =IF(E145>30,100000,IF(E145>24,120000,IF(E145>16,160000))) -> 120000 | R145: Nike | S145: 1.74 | T145: =TODAY() -> 46296 | U145: =_xlfn.DAYS(H144,T144) -> 1187 | V145: =IF(U145<180, "Pre contrato","Com Contrato em vigor") -> Com Contrato em vigor | W145: =I145*6 -> 9000000 | X145: =I145*13 -> 19500000
A146: Michael Richard Delgado de Oliveira | B146: CR Flamengo | C146: CR Flamengo | D146: Brasil | E146: =DATEDIF(F146,TODAY(),"Y") -> 30 | F146: 35136 | G146: 45526 | H146: 47118 | I146: 1600000 | J146: Dut's Mkt | K146: Atacante | L146: 0 | M146: 0 | N146: 18000000 | O146: =N146*3.5 -> 63000000 | P146: Direito | Q146: =IF(E146>30,100000,IF(E146>24,120000,IF(E146>16,160000))) -> 120000 | R146: Nike | S146: 1.66 | T146: =TODAY() -> 46296 | U146: =_xlfn.DAYS(H146,T146) -> 822 | V146: =IF(U146<180, "Pre contrato","Com Contrato em vigor") -> Com Contrato em vigor | W146: =I146*6 -> 9600000 | X146: =I146*13 -> 20800000
A147: Bruno Henrique Pinto | B147: CR Flamengo | C147: CR Flamengo | D147: Brasil | E147: =DATEDIF(F147,TODAY(),"Y") -> 35 | F147: 33237 | G147: 43488 | H147: 46387 | I147: 2000000 | J147: Sem empresario | K147: Atacante | L147: 2 | M147: 34 | N147: 10000000 | O147: =N147*3.5 -> 35000000 | P147: Direito | Q147: =IF(E147>30,100000,IF(E147>24,120000,IF(E147>16,160000))) -> 100000 | R147: Nike | S147: 1.84 | T147: =TODAY() -> 46296 | U147: =_xlfn.DAYS(H147,T147) -> 91 | V147: =IF(U147<180, "Pre contrato","Com Contrato em vigor") -> Pre contrato | W147: =I147*6 -> 12000000 | X147: =I147*13 -> 26000000
A148: Luiz de Araújo Guimarães Neto | B148: CR Flamengo | C148: CR Flamengo | D148: Brasil | E148: =DATEDIF(F148,TODAY(),"Y") -> 30 | F148: 35218 | G148: 45108 | H148: 46752 | I148: 1300000 | J148: Trust Football | K148: Atacante | L148: 1 | M148: 40 | N148: 12000000 | O148: =N148*3.5 -> 42000000 | P148: Esquerdo | Q148: =IF(E148>30,100000,IF(E148>24,120000,IF(E148>16,160000))) -> 120000 | R148: Adidas | S148: 1.75 | T148: =TODAY() -> 46296 | U148: =_xlfn.DAYS(H148,T148) -> 456 | V148: =IF(U148<180, "Pre contrato","Com Contrato em vigor") -> Com Contrato em vigor | W148: =I148*6 -> 7800000 | X148: =I148*13 -> 16900000
A149: Gonzalo Jordy Plata Jiménez | B149: CR Flamengo | C149: CR Flamengo | D149: Equador | E149: =DATEDIF(F149,TODAY(),"Y") -> 25 | F149: 36831 | G149: 45534 | H149: 47299 | I149: 450000 | J149: AS1 | K149: Atacante | L149: 0 | M149: 0 | N149: 7500000 | O149: =N149*3.5 -> 26250000 | P149: Esquerdo | Q149: =IF(E149>30,100000,IF(E149>24,120000,IF(E149>16,160000))) -> 120000 | R149: Adidas | S149: 1.78 | T149: =TODAY() -> 46296 | U149: =_xlfn.DAYS(H148,T148) -> 456 | V149: =IF(U149<180, "Pre contrato","Com Contrato em vigor") -> Com Contrato em vigor | W149: =I149*6 -> 2700000 | X149: =I149*13 -> 5850000
A150: Gabriel Barbosa Almeida | B150: CR Flamengo | C150: CR Flamengo | D150: Brasil | E150: =DATEDIF(F150,TODAY(),"Y") -> 30 | F150: 35307 | G150: 45658 | H150: 47118 | I150: 1800000 | J150: 4ComM | K150: Atacante | L150: 0 | M150: 0 | N150: 10000000 | O150: =N150*3.5 -> 35000000 | P150: Esquerdo | Q150: =IF(E150>30,100000,IF(E150>24,120000,IF(E150>16,160000))) -> 120000 | R150: Mizuno | S150: 1.78 | T150: =TODAY() -> 46296 | U150: =_xlfn.DAYS(H150,T150) -> 822 | V150: =IF(U150<180, "Pre contrato","Com Contrato em vigor") -> Com Contrato em vigor | W150: =I150*6 -> 10800000 | X150: =I150*13 -> 23400000
A151: Pedro Guilherme Abreu dos Santos | B151: CR Flamengo | C151: CR Flamengo | D151: Brasil | E151: =DATEDIF(F151,TODAY(),"Y") -> 29 | F151: 35601 | G151: 44197 | H151: 46752 | I151: 1350000 | J151: Bertolucci Sports | K151: Atacante | L151: 1 | M151: 90 | N151: 15000000 | O151: =N151*3.5 -> 52500000 | P151: Direito | Q151: =IF(E151>30,100000,IF(E151>24,120000,IF(E151>16,160000))) -> 120000 | R151: Adidas | S151: 1.85 | T151: =TODAY() -> 46296 | U151: =_xlfn.DAYS(H151,T151) -> 456 | V151: =IF(U151<180, "Pre contrato","Com Contrato em vigor") -> Com Contrato em vigor | W151: =I151*6 -> 8100000 | X151: =I151*13 -> 17550000
A152: Carlos Moises de Lima | B152: CR Flamengo | C152: CR Flamengo | D152: Brasil | E152: =DATEDIF(F152,TODAY(),"Y") -> 29 | F152: 35473 | G152: 45390 | H152: 46387 | I152: 200000 | J152: JBSports | K152: Atacante | L152: 0 | M152: 0 | N152: 3000000 | O152: =N152*3.5 -> 10500000 | P152: Esquerdo | Q152: =IF(E152>30,100000,IF(E152>24,120000,IF(E152>16,160000))) -> 120000 | R152: Nike | S152: 1.95 | T152: =TODAY() -> 46296 | U152: =_xlfn.DAYS(H152,T152) -> 91 | V152: =IF(U152<180, "Pre contrato","Com Contrato em vigor") -> Pre contrato | W152: =I152*6 -> 1200000 | X152: =I152*13 -> 2600000
A153: Léonardo César Jardim | B153: CR Vasco da Gama | C153: CR Vasco da Gama | D153: Brasil | E153: =DATEDIF(F153,TODAY(),"Y") -> 31 | F153: 34778 | G153: 44953 | H153: 46022 | I153: 230000 | J153: Talents Sports | K153: Goleiro | L153: 0 | M153: 0 | N153: 21000000 | O153: =N153*3.5 -> 73500000 | P153: Direito | Q153: =IF(E153>30,100000,IF(E153>24,120000,IF(E153>16,160000))) -> 100000 | R153: Nike | S153: 1.88 | T153: =TODAY() -> 46296 | U153: =_xlfn.DAYS(H152,T152) -> 91 | V153: =IF(U153<180, "Pre contrato","Com Contrato em vigor") -> Pre contrato | W153: =I153*6 -> 1380000 | X153: =I153*13 -> 2990000
A154: Keiller da Silva Nunes | B154: CR Vasco da Gama | C154: CR Vasco da Gama | D154: Brasil | E154: =DATEDIF(F154,TODAY(),"Y") -> 29 | F154: 35367 | G154: 45390 | H154: 46387 | I154: 100000 | J154: P&P Sport Management S.A.M. | K154: Goleiro | L154: 0 | M154: 0 | N154: 3000000 | O154: =N154*3.5 -> 10500000 | P154: Direito | Q154: =IF(E154>30,100000,IF(E154>24,120000,IF(E154>16,160000))) -> 120000 | R154: Nike | S154: 1.93 | T154: =TODAY() -> 46296 | U154: =_xlfn.DAYS(H154,T154) -> 91 | V154: =IF(U154<180, "Pre contrato","Com Contrato em vigor") -> Pre contrato | W154: =I154*6 -> 600000 | X154: =I154*13 -> 1300000
A155: Hedhe Halls Rocha da Silva | B155: CR Vasco da Gama | C155: CR Vasco da Gama | D155: Brasil | E155: =DATEDIF(F155,TODAY(),"Y") -> 27 | F155: 36328 | G155: 45108 | H155: 46022 | I155: 75000 | J155: Sem empresario | K155: Goleiro | L155: 0 | M155: 0 | N155: 2000000 | O155: =N155*3.5 -> 7000000 | P155: Direito | Q155: =IF(E155>30,100000,IF(E155>24,120000,IF(E155>16,160000))) -> 120000 | R155: Nike | S155: 1.98 | T155: =TODAY() -> 46296 | U155: =_xlfn.DAYS(H155,T155) -> -274 | V155: =IF(U155<180, "Pre contrato","Com Contrato em vigor") -> Pre contrato | W155: =I155*6 -> 450000 | X155: =I155*13 -> 975000
A156: Phillipe Gabriel Pires de Oliveira | B156: CR Vasco da Gama | C156: CR Vasco da Gama | D156: Brasil | E156: =DATEDIF(F156,TODAY(),"Y") -> 20 | F156: 38751 | G156: 45292 | H156: 46022 | I156: 110000 | J156: All In Sports | K156: Goleiro | L156: 0 | M156: 0 | N156: 1500000 | O156: =N156*3.5 -> 5250000 | P156: Direito | Q156: =IF(E156>30,100000,IF(E156>24,120000,IF(E156>16,160000))) -> 160000 | R156: Nike | S156: 1.96 | T156: =TODAY() -> 46296 | U156: =_xlfn.DAYS(H156,T156) -> -274 | V156: =IF(U156<180, "Pre contrato","Com Contrato em vigor") -> Pre contrato | W156: =I156*6 -> 660000 | X156: =I156*13 -> 1430000
A157: João Victor Da Silva Marcelino | B157: CR Vasco da Gama | C157: CR Vasco da Gama | D157: Brasil | E157: =DATEDIF(F157,TODAY(),"Y") -> 28 | F157: 35993 | G157: 45292 | H157: 46022 | I157: 270000 | J157: Talents Sports | K157: Zagueiro | L157: 0 | M157: 0 | N157: 5000000 | O157: =N157*3.5 -> 17500000 | P157: Direito | Q157: =IF(E157>30,100000,IF(E157>24,120000,IF(E157>16,160000))) -> 120000 | R157: Nike | S157: 1.87 | T157: =TODAY() -> 46296 | U157: =_xlfn.DAYS(H156,T156) -> -274 | V157: =IF(U157<180, "Pre contrato","Com Contrato em vigor") -> Pre contrato | W157: =I157*6 -> 1620000 | X157: =I157*13 -> 3510000
A158: Leonardo Pinheiro da Conceição | B158: CR Vasco da Gama | C158: CR Vasco da Gama | D158: Brasil | E158: =DATEDIF(F158,TODAY(),"Y") -> 30 | F158: 35130 | G158: 44927 | H158: 46022 | I158: 300000 | J158: Sem empresario | K158: Zagueiro | L158: 0 | M158: 0 | N158: 7000000 | O158: =N158*3.5 -> 24500000 | P158: Esquerdo | Q158: =IF(E158>30,100000,IF(E158>24,120000,IF(E158>16,160000))) -> 120000 | R158: New Balance | S158: 1.83 | T158: =TODAY() -> 46296 | U158: =_xlfn.DAYS(H158,T158) -> -274 | V158: =IF(U158<180, "Pre contrato","Com Contrato em vigor") -> Pre contrato | W158: =I158*6 -> 1800000 | X158: =I158*13 -> 3900000
A159: Manuel Vicente Capasso | B159: CR Vasco da Gama | C159: CR Vasco da Gama | D159: Argentina | E159: =DATEDIF(F159,TODAY(),"Y") -> 30 | F159: 35174 | G159: 44976 | H159: 46022 | I159: 220000 | J159: DG Football Agency | K159: Zagueiro | L159: 2 | M159: 13 | N159: 5000000 | O159: =N159*3.5 -> 17500000 | P159: Direito | Q159: =IF(E159>30,100000,IF(E159>24,120000,IF(E159>16,160000))) -> 120000 | R159: Nike | S159: 1.88 | T159: =TODAY() -> 46296 | U159: =_xlfn.DAYS(H159,T159) -> -274 | V159: =IF(U159<180, "Pre contrato","Com Contrato em vigor") -> Pre contrato | W159: =I159*6 -> 1320000 | X159: =I159*13 -> 2860000
A160: Gary Alexis Medel Soto | B160: CR Vasco da Gama | C160: CR Vasco da Gama | D160: Chile | E160: =DATEDIF(F160,TODAY(),"Y") -> 39 | F160: 31992 | G160: 44976 | H160: 46022 | I160: 400000 | J160: Vibra Futbol | K160: Zagueiro | L160: 1 | M160: 21 | N160: 1250000 | O160: =N160*3.5 -> 4375000 | P160: Direito | Q160: =IF(E160>30,100000,IF(E160>24,120000,IF(E160>16,160000))) -> 100000 | R160: Nike | S160: 1.71 | T160: =TODAY() -> 46296 | U160: =_xlfn.DAYS(H160,T160) -> -274 | V160: =IF(U160<180, "Pre contrato","Com Contrato em vigor") -> Pre contrato | W160: =I160*6 -> 2400000 | X160: =I160*13 -> 5200000
A161: Maicon Pereira Roque | B161: CR Vasco da Gama | C161: CR Vasco da Gama | D161: Brasil | E161: =DATEDIF(F161,TODAY(),"Y") -> 38 | F161: 32400 | G161: 45108 | H161: 46022 | I161: 350000 | J161: Carlos Leite | K161: Zagueiro | L161: 1 | M161: 26 | N161: 2000000 | O161: =N161*3.5 -> 7000000 | P161: Direito | Q161: =IF(E161>30,100000,IF(E161>24,120000,IF(E161>16,160000))) -> 100000 | R161: Mizuno | S161: 1.91 | T161: =TODAY() -> 46296 | U161: =_xlfn.DAYS(H160,T160) -> -274 | V161: =IF(U161<180, "Pre contrato","Com Contrato em vigor") -> Pre contrato | W161: =I161*6 -> 2100000 | X161: =I161*13 -> 4550000
A162: Matheus dos Santos Miranda | B162: CR Vasco da Gama | C162: CR Vasco da Gama | D162: Brasil | E162: =DATEDIF(F162,TODAY(),"Y") -> 26 | F162: 36544 | G162: 45338 | H162: 45658 | I162: 60000 | J162: Marcio Bittencourt Sports | K162: Zagueiro | L162: 0 | M162: 0 | N162: 1200000 | O162: =N162*3.5 -> 4200000 | P162: Direito | Q162: =IF(E162>30,100000,IF(E162>24,120000,IF(E162>16,160000))) -> 120000 | R162: Nike | S162: 1.81 | T162: =TODAY() -> 46296 | U162: =_xlfn.DAYS(H162,T162) -> -638 | V162: =IF(U162<180, "Pre contrato","Com Contrato em vigor") -> Pre contrato | W162: =I162*6 -> 360000 | X162: =I162*13 -> 780000
A163: Lucas Piton Crivellaro | B163: CR Vasco da Gama | C163: CR Vasco da Gama | D163: Brasil | E163: =DATEDIF(F163,TODAY(),"Y") -> 25 | F163: 36808 | G163: 44927 | H163: 47118 | I163: 360000 | J163: Gilvan Costa | K163: Lateral Esquerdo | L163: 2 | M163: 21 | N163: 13000000 | O163: =N163*3.5 -> 45500000 | P163: Esquerdo | Q163: =IF(E163>30,100000,IF(E163>24,120000,IF(E163>16,160000))) -> 120000 | R163: Puma | S163: 1.75 | T163: =TODAY() -> 46296 | U163: =_xlfn.DAYS(H163,T163) -> 822 | V163: =IF(U163<180, "Pre contrato","Com Contrato em vigor") -> Com Contrato em vigor | W163: =I163*6 -> 2160000 | X163: =I163*13 -> 4680000
A164: Victor Luís Chuab Zamblauskas | B164: CR Vasco da Gama | C164: CR Vasco da Gama | D164: Brasil | E164: =DATEDIF(F164,TODAY(),"Y") -> 33 | F164: 34143 | G164: 45327 | H164: 45658 | I164: 300000 | J164: LINK SPORTS | K164: Lateral Esquerdo | L164: 1 | M164: 32 | N164: 1500000 | O164: =N164*3.5 -> 5250000 | P164: Esquerdo | Q164: =IF(E164>30,100000,IF(E164>24,120000,IF(E164>16,160000))) -> 100000 | R164: Nike | S164: 1.77 | T164: =TODAY() -> 46296 | U164: =_xlfn.DAYS(H164,T164) -> -638 | V164: =IF(U164<180, "Pre contrato","Com Contrato em vigor") -> Pre contrato | W164: =I164*6 -> 1800000 | X164: =I164*13 -> 3900000
A165: José Luis Rodríguez Bebanz | B165: CR Vasco da Gama | C165: CR Vasco da Gama | D165: Uruguai | E165: =DATEDIF(F165,TODAY(),"Y") -> 29 | F165: 35503 | G165: 44930 | H165: 46022 | I165: 333000 | J165: Paco Casal | K165: Lateral Direito | L165: 1 | M165: 19 | N165: 6700000 | O165: =N165*3.5 -> 23450000 | P165: Direito | Q165: =IF(E165>30,100000,IF(E165>24,120000,IF(E165>16,160000))) -> 120000 | R165: Puma | S165: 1.83 | T165: =TODAY() -> 46296 | U165: =_xlfn.DAYS(H164,T164) -> -638 | V165: =IF(U165<180, "Pre contrato","Com Contrato em vigor") -> Pre contrato | W165: =I165*6 -> 1998000 | X165: =I165*13 -> 4329000
A166: Paulo Henrique de Oliveira Alves | B166: CR Vasco da Gama | C166: CR Vasco da Gama | D166: Brasil | E166: =DATEDIF(F166,TODAY(),"Y") -> 30 | F166: 35271 | G166: 45292 | H166: 46752 | I166: 350000 | J166: Sem empresario | K166: Lateral Direito | L166: 1 | M166: 10 | N166: 4000000 | O166: =N166*3.5 -> 14000000 | P166: Direito | Q166: =IF(E166>30,100000,IF(E166>24,120000,IF(E166>16,160000))) -> 120000 | R166: Adidas | S166: 1.75 | T166: =TODAY() -> 46296 | U166: =_xlfn.DAYS(H166,T166) -> 456 | V166: =IF(U166<180, "Pre contrato","Com Contrato em vigor") -> Com Contrato em vigor | W166: =I166*6 -> 2100000 | X166: =I166*13 -> 4550000
A167: Jair Rodrigues Júnior | B167: CR Vasco da Gama | C167: CR Vasco da Gama | D167: Brasil | E167: =DATEDIF(F167,TODAY(),"Y") -> 32 | F167: 34572 | G167: 44939 | H167: 46022 | I167: 280000 | J167: Prattes Group | K167: Volante | L167: 1 | M167: 26 | N167: 8000000 | O167: =N167*3.5 -> 28000000 | P167: Direito | Q167: =IF(E167>30,100000,IF(E167>24,120000,IF(E167>16,160000))) -> 100000 | R167: Adidas | S167: 1.78 | T167: =TODAY() -> 46296 | U167: =_xlfn.DAYS(H167,T167) -> -274 | V167: =IF(U167<180, "Pre contrato","Com Contrato em vigor") -> Pre contrato | W167: =I167*6 -> 1680000 | X167: =I167*13 -> 3640000
A168: Josef de Souza Dias | B168: CR Vasco da Gama | C168: CR Vasco da Gama | D168: Brasil | E168: =DATEDIF(F168,TODAY(),"Y") -> 37 | F168: 32550 | G168: 45487 | H168: 46022 | I168: 400000 | J168: Carlos Leite | K168: Volante | L168: 2 | M168: 31 | N168: 1000000 | O168: =N168*3.5 -> 3500000 | P168: Direito | Q168: =IF(E168>30,100000,IF(E168>24,120000,IF(E168>16,160000))) -> 100000 | R168: Nike | S168: 1.88 | T168: =TODAY() -> 46296 | U168: =_xlfn.DAYS(H168,T168) -> -274 | V168: =IF(U168<180, "Pre contrato","Com Contrato em vigor") -> Pre contrato | W168: =I168*6 -> 2400000 | X168: =I168*13 -> 5200000
A169: Juan Sebastián Sforza | B169: CR Vasco da Gama | C169: CR Vasco da Gama | D169: Brasil | E169: =DATEDIF(F169,TODAY(),"Y") -> 24 | F169: 37301 | G169: 45341 | H169: 47118 | I169: 350000 | J169: Primotempo | K169: Volante | L169: 1 | M169: 31 | N169: 12000000 | O169: =N169*3.5 -> 42000000 | P169: Direito | Q169: =IF(E169>30,100000,IF(E169>24,120000,IF(E169>16,160000))) -> 160000 | R169: Nike | S169: 1.79 | T169: =TODAY() -> 46296 | U169: =_xlfn.DAYS(H168,T168) -> -274 | V169: =IF(U169<180, "Pre contrato","Com Contrato em vigor") -> Pre contrato | W169: =I169*6 -> 2100000 | X169: =I169*13 -> 4550000
A170: José Gabriel dos Santos Silva | B170: CR Vasco da Gama | C170: CR Vasco da Gama | D170: Brasil | E170: =DATEDIF(F170,TODAY(),"Y") -> 27 | F170: 36181 | G170: 44603 | H170: 46022 | I170: 150000 | J170: Sem empresario | K170: Volante | L170: 0 | M170: 0 | N170: 3000000 | O170: =N170*3.5 -> 10500000 | P170: Direito | Q170: =IF(E170>30,100000,IF(E170>24,120000,IF(E170>16,160000))) -> 120000 | R170: Nike | S170: 1.84 | T170: =TODAY() -> 46296 | U170: =_xlfn.DAYS(H170,T170) -> -274 | V170: =IF(U170<180, "Pre contrato","Com Contrato em vigor") -> Pre contrato | W170: =I170*6 -> 900000 | X170: =I170*13 -> 1950000
A171: Hugo Moura Arruda da Silva | B171: CR Vasco da Gama | C171: CR Vasco da Gama | D171: Brasil | E171: =DATEDIF(F171,TODAY(),"Y") -> 28 | F171: 35798 | G171: 45292 | H171: 46752 | I171: 460000 | J171: Brazil Soccer | K171: Volante | L171: 1 | M171: 12 | N171: 4000000 | O171: =N171*3.5 -> 14000000 | P171: Direito | Q171: =IF(E171>30,100000,IF(E171>24,120000,IF(E171>16,160000))) -> 120000 | R171: Nike | S171: 1.77 | T171: =TODAY() -> 46296 | U171: =_xlfn.DAYS(H171,T171) -> 456 | V171: =IF(U171<180, "Pre contrato","Com Contrato em vigor") -> Com Contrato em vigor | W171: =I171*6 -> 2760000 | X171: =I171*13 -> 5980000
A172: Bruno Conceição Praxedes | B172: CR Vasco da Gama | C172: CR Vasco da Gama | D172: Brasil | E172: =DATEDIF(F172,TODAY(),"Y") -> 24 | F172: 37295 | G172: 44377 | H172: 46203 | I172: 400000 | J172: LINK SPORTS | K172: Meio Campo | L172: 0 | M172: 0 | N172: 6000000 | O172: =N172*3.5 -> 21000000 | P172: Direito | Q172: =IF(E172>30,100000,IF(E172>24,120000,IF(E172>16,160000))) -> 160000 | R172: Adidas | S172: 1.86 | T172: =TODAY() -> 46296 | U172: =_xlfn.DAYS(H172,T172) -> -93 | V172: =IF(U172<180, "Pre contrato","Com Contrato em vigor") -> Pre contrato | W172: =I172*6 -> 2400000 | X172: =I172*13 -> 5200000
A173: Pablo Ignacio Galdames Millán | B173: CR Vasco da Gama | C173: CR Vasco da Gama | D173: Chile | E173: =DATEDIF(F173,TODAY(),"Y") -> 29 | F173: 35429 | G173: 45327 | H173: 46203 | I173: 380000 | J173: Fatto Gestão | K173: Meio Campo | L173: 0 | M173: 0 | N173: 3500000 | O173: =N173*3.5 -> 12250000 | P173: Direito | Q173: =IF(E173>30,100000,IF(E173>24,120000,IF(E173>16,160000))) -> 120000 | R173: Adidas | S173: 1.73 | T173: =TODAY() -> 46296 | U173: =_xlfn.DAYS(H172,T172) -> -93 | V173: =IF(U173<180, "Pre contrato","Com Contrato em vigor") -> Pre contrato | W173: =I173*6 -> 2280000 | X173: =I173*13 -> 4940000
A174: Maxime Dominguez | B174: CR Vasco da Gama | C174: CR Vasco da Gama | D174: Suiça | E174: =DATEDIF(F174,TODAY(),"Y") -> 30 | F174: 35096 | G174: 45537 | H174: 46934 | I174: 320000 | J174: VPA SPORTS INTERNATIONAL LTD | K174: Meio Campo | L174: 0 | M174: 0 | N174: 4000000 | O174: =N174*3.5 -> 14000000 | P174: Direito | Q174: =IF(E174>30,100000,IF(E174>24,120000,IF(E174>16,160000))) -> 120000 | R174: Nike | S174: 1.73 | T174: =TODAY() -> 46296 | U174: =_xlfn.DAYS(H174,T174) -> 638 | V174: =IF(U174<180, "Pre contrato","Com Contrato em vigor") -> Com Contrato em vigor | W174: =I174*6 -> 1920000 | X174: =I174*13 -> 4160000
A175: João Pedro Murilo de Paula Morais | B175: CR Vasco da Gama | C175: CR Vasco da Gama | D175: Brasil | E175: =DATEDIF(F175,TODAY(),"Y") -> 21 | F175: 38461 | G175: 45444 | H175: 46752 | I175: 375000 | J175: LINK SPORTS | K175: Meio Campo | L175: 1 | M175: 10 | N175: 1200000 | O175: =N175*3.5 -> 4200000 | P175: Direito | Q175: =IF(E175>30,100000,IF(E175>24,120000,IF(E175>16,160000))) -> 160000 | R175: Nike | S175: 1.76 | T175: =TODAY() -> 46296 | U175: =_xlfn.DAYS(H175,T175) -> 456 | V175: =IF(U175<180, "Pre contrato","Com Contrato em vigor") -> Com Contrato em vigor | W175: =I175*6 -> 2250000 | X175: =I175*13 -> 4875000
A176: Philippe Coutinho Correia | B176: CR Vasco da Gama | C176: CR Vasco da Gama | D176: Brasil | E176: =DATEDIF(F176,TODAY(),"Y") -> 34 | F176: 33767 | G176: 45483 | H176: 45838 | I176: 950000 | J176: Sports Invest UK ltd | K176: Meio Campo | L176: 1 | M176: 15 | N176: 10000000 | O176: =N176*3.5 -> 35000000 | P176: Direito | Q176: =IF(E176>30,100000,IF(E176>24,120000,IF(E176>16,160000))) -> 100000 | R176: Nike | S176: 1.73 | T176: =TODAY() -> 46296 | U176: =_xlfn.DAYS(H176,T176) -> -458 | V176: =IF(U176<180, "Pre contrato","Com Contrato em vigor") -> Pre contrato | W176: =I176*6 -> 5700000 | X176: =I176*13 -> 12350000
A177: Dimitri Payet | B177: CR Vasco da Gama | C177: CR Vasco da Gama | D177: França | E177: =DATEDIF(F177,TODAY(),"Y") -> 39 | F177: 31865 | G177: 45155 | H177: 45838 | I177: 850000 | J177: J.Gomes Avocat | K177: Meio Campo | L177: 1 | M177: 16 | N177: 6000000 | O177: =N177*3.5 -> 21000000 | P177: Direito | Q177: =IF(E177>30,100000,IF(E177>24,120000,IF(E177>16,160000))) -> 100000 | R177: Puma | S177: 1.75 | T177: =TODAY() -> 46296 | U177: =_xlfn.DAYS(H176,T176) -> -458 | V177: =IF(U177<180, "Pre contrato","Com Contrato em vigor") -> Pre contrato | W177: =I177*6 -> 5100000 | X177: =I177*13 -> 11050000
A178: Cauan Lucas Barros da Luz | B178: CR Vasco da Gama | C178: CR Vasco da Gama | D178: Brasil | E178: =DATEDIF(F178,TODAY(),"Y") -> 22 | F178: 38113 | G178: 45337 | H178: 45838 | I178: 100000 | J178: Trust Football | K178: Meio Campo | L178: 1 | M178: 10 | N178: 500000 | O178: =N178*3.5 -> 1750000 | P178: Direito | Q178: =IF(E178>30,100000,IF(E178>24,120000,IF(E178>16,160000))) -> 160000 | R178: Nike | S178: 1.83 | T178: =TODAY() -> 46296 | U178: =_xlfn.DAYS(H178,T178) -> -458 | V178: =IF(U178<180, "Pre contrato","Com Contrato em vigor") -> Pre contrato | W178: =I178*6 -> 600000 | X178: =I178*13 -> 1300000
A179: Jean David Meneses Villarroel | B179: CR Vasco da Gama | C179: CR Vasco da Gama | D179: Chile | E179: =DATEDIF(F179,TODAY(),"Y") -> 33 | F179: 34044 | G179: 45531 | H179: 46203 | I179: 510000 | J179: Mundo Futuro Chile | K179: Atacante | L179: 1 | M179: 11 | N179: 7000000 | O179: =N179*3.5 -> 24500000 | P179: Direito | Q179: =IF(E179>30,100000,IF(E179>24,120000,IF(E179>16,160000))) -> 100000 | R179: Nike | S179: 1.63 | T179: =TODAY() -> 46296 | U179: =_xlfn.DAYS(H179,T179) -> -93 | V179: =IF(U179<180, "Pre contrato","Com Contrato em vigor") -> Pre contrato | W179: =I179*6 -> 3060000 | X179: =I179*13 -> 6630000
A180: Emerson Rivaldo Rodríguez Valois | B180: CR Vasco da Gama | C180: CR Vasco da Gama | D180: Colômbia | E180: =DATEDIF(F180,TODAY(),"Y") -> 26 | F180: 36763 | G180: 45489 | H180: 45838 | I180: 260000 | J180: ISC | K180: Atacante | L180: 0 | M180: 0 | N180: 6000000 | O180: =N180*3.5 -> 21000000 | P180: Direito | Q180: =IF(E180>30,100000,IF(E180>24,120000,IF(E180>16,160000))) -> 120000 | R180: Nike | S180: 1.74 | T180: =TODAY() -> 46296 | U180: =_xlfn.DAYS(H180,T180) -> -458 | V180: =IF(U180<180, "Pre contrato","Com Contrato em vigor") -> Pre contrato | W180: =I180*6 -> 1560000 | X180: =I180*13 -> 3380000
A181: David Corrêa da Fonseca | B181: CR Vasco da Gama | C181: CR Vasco da Gama | D181: Brasil | E181: =DATEDIF(F181,TODAY(),"Y") -> 30 | F181: 34989 | G181: 45302 | H181: 45657 | I181: 560000 | J181: LINK SPORTS | K181: Atacante | L181: 1 | M181: 30 | N181: 4000000 | O181: =N181*3.5 -> 14000000 | P181: Direito | Q181: =IF(E181>30,100000,IF(E181>24,120000,IF(E181>16,160000))) -> 120000 | R181: Nike | S181: 1.79 | T181: =TODAY() -> 46296 | U181: =_xlfn.DAYS(H180,T180) -> -458 | V181: =IF(U181<180, "Pre contrato","Com Contrato em vigor") -> Pre contrato | W181: =I181*6 -> 3360000 | X181: =I181*13 -> 7280000
A182: Sérgio Antonio da Luz Junior | B182: CR Vasco da Gama | C182: CR Vasco da Gama | D182: Brasil | E182: =DATEDIF(F182,TODAY(),"Y") -> 31 | F182: 34795 | G182: 45108 | H182: 46022 | I182: 160000 | J182: Granja Sports | K182: Atacante | L182: 0 | M182: 0 | N182: 700000 | O182: =N182*3.5 -> 2450000 | P182: Direito | Q182: =IF(E182>30,100000,IF(E182>24,120000,IF(E182>16,160000))) -> 100000 | R182: Adidas | S182: 1.8 | T182: =TODAY() -> 46296 | U182: =_xlfn.DAYS(H182,T182) -> -274 | V182: =IF(U182<180, "Pre contrato","Com Contrato em vigor") -> Pre contrato | W182: =I182*6 -> 960000 | X182: =I182*13 -> 2080000
A183: Adson Ferreira Soares | B183: CR Vasco da Gama | C183: CR Vasco da Gama | D183: Brasil | E183: =DATEDIF(F183,TODAY(),"Y") -> 25 | F183: 36805 | G183: 45315 | H183: 46752 | I183: 650000 | J183: Fabio Mello Sports | K183: Atacante | L183: 1 | M183: 14 | N183: 12000000 | O183: =N183*3.5 -> 42000000 | P183: Esquerdo | Q183: =IF(E183>30,100000,IF(E183>24,120000,IF(E183>16,160000))) -> 120000 | R183: Adidas | S183: 1.71 | T183: =TODAY() -> 46296 | U183: =_xlfn.DAYS(H183,T183) -> 456 | V183: =IF(U183<180, "Pre contrato","Com Contrato em vigor") -> Com Contrato em vigor | W183: =I183*6 -> 3900000 | X183: =I183*13 -> 8450000
A184: Rosicley Pereira da Silva | B184: CR Vasco da Gama | C184: CR Vasco da Gama | D184: Brasil | E184: =DATEDIF(F184,TODAY(),"Y") -> 33 | F184: 34081 | G184: 45147 | H184: 45663 | I184: 250000 | J184: Sem empresario | K184: Atacante | L184: 3 | M184: 31 | N184: 1400000 | O184: =N184*3.5 -> 4900000 | P184: Direito | Q184: =IF(E184>30,100000,IF(E184>24,120000,IF(E184>16,160000))) -> 100000 | R184: Adidas | S184: 1.7 | T184: =TODAY() -> 46296 | U184: =_xlfn.DAYS(H183,T183) -> 456 | V184: =IF(U184<180, "Pre contrato","Com Contrato em vigor") -> Com Contrato em vigor | W184: =I184*6 -> 1500000 | X184: =I184*13 -> 3250000
A185: Alex Teixeira Santos | B185: CR Vasco da Gama | C185: CR Vasco da Gama | D185: Brasil | E185: =DATEDIF(F185,TODAY(),"Y") -> 36 | F185: 32879 | G185: 45488 | H185: 46022 | I185: 450000 | J185: REASON FOOTBALL INVESTMENTS | K185: Atacante | L185: 1 | M185: 21 | N185: 500000 | O185: =N185*3.5 -> 1750000 | P185: Esquerdo | Q185: =IF(E185>30,100000,IF(E185>24,120000,IF(E185>16,160000))) -> 100000 | R185: Nike | S185: 1.73 | T185: =TODAY() -> 46296 | U185: =_xlfn.DAYS(H185,T185) -> -274 | V185: =IF(U185<180, "Pre contrato","Com Contrato em vigor") -> Pre contrato | W185: =I185*6 -> 2700000 | X185: =I185*13 -> 5850000
A186: Clayton Fernandes Silva | B186: CR Vasco da Gama | C186: CR Vasco da Gama | D186: Brasil | E186: =DATEDIF(F186,TODAY(),"Y") -> 27 | F186: 36171 | G186: 45505 | H186: 45838 | I186: 200000 | J186: Sem empresario | K186: Atacante | L186: 1 | M186: 21 | N186: 7000000 | O186: =N186*3.5 -> 24500000 | P186: Direito | Q186: =IF(E186>30,100000,IF(E186>24,120000,IF(E186>16,160000))) -> 120000 | R186: Adidas | S186: 1.84 | T186: =TODAY() -> 46296 | U186: =_xlfn.DAYS(H186,T186) -> -458 | V186: =IF(U186<180, "Pre contrato","Com Contrato em vigor") -> Pre contrato | W186: =I186*6 -> 1200000 | X186: =I186*13 -> 2600000
A187: Pablo Ezequiel Vegetti Pfaffen | B187: CR Vasco da Gama | C187: CR Vasco da Gama | D187: Brasil | E187: =DATEDIF(F187,TODAY(),"Y") -> 37 | F187: 32431 | G187: 45140 | H187: 46022 | I187: 350000 | J187: Futbol Cracks | K187: Atacante | L187: 1 | M187: 16 | N187: 1700000 | O187: =N187*3.5 -> 5950000 | P187: Direito | Q187: =IF(E187>30,100000,IF(E187>24,120000,IF(E187>16,160000))) -> 100000 | R187: Nike | S187: 1.87 | T187: =TODAY() -> 46296 | U187: =_xlfn.DAYS(H187,T187) -> -274 | V187: =IF(U187<180, "Pre contrato","Com Contrato em vigor") -> Pre contrato | W187: =I187*6 -> 2100000 | X187: =I187*13 -> 4550000
A188: Matheus Henrique Teixeira | B188: Criciúma EC | C188: Criciúma EC | D188: Brasil | E188: =DATEDIF(F188,TODAY(),"Y") -> 27 | F188: 36227 | G188: 44228 | H188: 46022 | I188: 75000 | J188: AGON | K188: Goleiro | L188: 0 | M188: 0 | N188: 120000 | O188: =N188*3.5 -> 420000 | P188: Direito | Q188: =IF(E188>30,100000,IF(E188>24,120000,IF(E188>16,160000))) -> 120000 | R188: Adidas | S188: 1.87 | T188: =TODAY() -> 46296 | U188: =_xlfn.DAYS(H187,T187) -> -274 | V188: =IF(U188<180, "Pre contrato","Com Contrato em vigor") -> Pre contrato | W188: =I188*6 -> 450000 | X188: =I188*13 -> 975000
A189: Luiz Gustavo Almeida Pinto | B189: Criciúma EC | C189: Criciúma EC | D189: Brasil | E189: =DATEDIF(F189,TODAY(),"Y") -> 33 | F189: 34038 | G189: 44238 | H189: 46022 | I189: 50000 | J189: PECBOL SPORTS | K189: Goleiro | L189: 0 | M189: 0 | N189: 75000 | O189: =N189*3.5 -> 262500 | P189: Direito | Q189: =IF(E189>30,100000,IF(E189>24,120000,IF(E189>16,160000))) -> 100000 | R189: Adidas | S189: 1.87 | T189: =TODAY() -> 46296 | U189: =_xlfn.DAYS(H189,T189) -> -274 | V189: =IF(U189<180, "Pre contrato","Com Contrato em vigor") -> Pre contrato | W189: =I189*6 -> 300000 | X189: =I189*13 -> 650000
A190: Alisson Machado dos Santos | B190: Criciúma EC | C190: Criciúma EC | D190: Brasil | E190: =DATEDIF(F190,TODAY(),"Y") -> 31 | F190: 34858 | G190: 44580 | H190: 46022 | I190: 30000 | J190: Nauru BR | K190: Goleiro | L190: 0 | M190: 0 | N190: 150000 | O190: =N190*3.5 -> 525000 | P190: Direito | Q190: =IF(E190>30,100000,IF(E190>24,120000,IF(E190>16,160000))) -> 100000 | R190: Adidas | S190: 1.88 | T190: =TODAY() -> 46296 | U190: =_xlfn.DAYS(H190,T190) -> -274 | V190: =IF(U190<180, "Pre contrato","Com Contrato em vigor") -> Pre contrato | W190: =I190*6 -> 180000 | X190: =I190*13 -> 390000
A191: Tobias Pereira Figueiredo | B191: Criciúma EC | C191: Criciúma EC | D191: Brasil | E191: =DATEDIF(F191,TODAY(),"Y") -> 32 | F191: 34367 | G191: 45118 | H191: 46387 | I191: 45000 | J191: Proeleven S.A. | K191: Zagueiro | L191: 0 | M191: 0 | N191: 100000 | O191: =N191*3.5 -> 350000 | P191: Direito | Q191: =IF(E191>30,100000,IF(E191>24,120000,IF(E191>16,160000))) -> 100000 | R191: Adidas | S191: 1.87 | T191: =TODAY() -> 46296 | U191: =_xlfn.DAYS(H191,T191) -> 91 | V191: =IF(U191<180, "Pre contrato","Com Contrato em vigor") -> Pre contrato | W191: =I191*6 -> 270000 | X191: =I191*13 -> 585000
A192: Wilker José Ángel Romero | B192: Criciúma EC | C192: Criciúma EC | D192: Venezuela | E192: =DATEDIF(F192,TODAY(),"Y") -> 33 | F192: 34046 | G192: 45331 | H192: 45657 | I192: 30000 | J192: AFV | K192: Zagueiro | L192: 0 | M192: 0 | N192: 200000 | O192: =N192*3.5 -> 700000 | P192: Direito | Q192: =IF(E192>30,100000,IF(E192>24,120000,IF(E192>16,160000))) -> 100000 | R192: Adidas | S192: 1.9 | T192: =TODAY() -> 46296 | U192: =_xlfn.DAYS(H191,T191) -> 91 | V192: =IF(U192<180, "Pre contrato","Com Contrato em vigor") -> Pre contrato | W192: =I192*6 -> 180000 | X192: =I192*13 -> 390000
A193: Rodrigo Fagundes de Freitas | B193: Criciúma EC | C193: Criciúma EC | D193: Brasil | E193: =DATEDIF(F193,TODAY(),"Y") -> 39 | F193: 31846 | G193: 44337 | H193: 45649 | I193: 35000 | J193: Sem empresario | K193: Zagueiro | L193: 0 | M193: 0 | N193: 150000 | O193: =N193*3.5 -> 525000 | P193: Direito | Q193: =IF(E193>30,100000,IF(E193>24,120000,IF(E193>16,160000))) -> 100000 | R193: Adidas | S193: 1.87 | T193: =TODAY() -> 46296 | U193: =_xlfn.DAYS(H193,T193) -> -647 | V193: =IF(U193<180, "Pre contrato","Com Contrato em vigor") -> Pre contrato | W193: =I193*6 -> 210000 | X193: =I193*13 -> 455000
A194: Walisson Moreira Farias Maia | B194: Criciúma EC | C194: Criciúma EC | D194: Brasil | E194: =DATEDIF(F194,TODAY(),"Y") -> 35 | F194: 33471 | G194: 45331 | H194: 45649 | I194: 30000 | J194: TL Sport | K194: Zagueiro | L194: 0 | M194: 0 | N194: 100000 | O194: =N194*3.5 -> 350000 | P194: Direito | Q194: =IF(E194>30,100000,IF(E194>24,120000,IF(E194>16,160000))) -> 100000 | R194: Adidas | S194: 1.88 | T194: =TODAY() -> 46296 | U194: =_xlfn.DAYS(H194,T194) -> -647 | V194: =IF(U194<180, "Pre contrato","Com Contrato em vigor") -> Pre contrato | W194: =I194*6 -> 180000 | X194: =I194*13 -> 390000
A195: Miguel Ángel Trauco Saavedra | B195: Criciúma EC | C195: Criciúma EC | D195: Perú | E195: =DATEDIF(F195,TODAY(),"Y") -> 34 | F195: 33841 | G195: 45323 | H195: 45657 | I195: 100000 | J195: MIRAGEDEPOR | K195: Lateral Esquerdo | L195: 0 | M195: 0 | N195: 150000 | O195: =N195*3.5 -> 525000 | P195: Esquerdo | Q195: =IF(E195>30,100000,IF(E195>24,120000,IF(E195>16,160000))) -> 100000 | R195: Adidas | S195: 1.75 | T195: =TODAY() -> 46296 | U195: =_xlfn.DAYS(H195,T195) -> -639 | V195: =IF(U195<180, "Pre contrato","Com Contrato em vigor") -> Pre contrato | W195: =I195*6 -> 600000 | X195: =I195*13 -> 1300000
A196: Marcelo Hermes | B196: Criciúma EC | C196: Criciúma EC | D196: Brasil | E196: =DATEDIF(F196,TODAY(),"Y") -> 31 | F196: 34731 | G196: 44613 | H196: 46022 | I196: 120000 | J196: MPX SPORTS | K196: Lateral Esquerdo | L196: 0 | M196: 0 | N196: 250000 | O196: =N196*3.5 -> 875000 | P196: Esquerdo | Q196: =IF(E196>30,100000,IF(E196>24,120000,IF(E196>16,160000))) -> 100000 | R196: Adidas | S196: 1.77 | T196: =TODAY() -> 46296 | U196: =_xlfn.DAYS(H195,T195) -> -639 | V196: =IF(U196<180, "Pre contrato","Com Contrato em vigor") -> Pre contrato | W196: =I196*6 -> 720000 | X196: =I196*13 -> 1560000
A197: Luis Eduardo Marques dos Santos | B197: Criciúma EC | C197: Criciúma EC | D197: Brasil | E197: =DATEDIF(F197,TODAY(),"Y") -> 29 | F197: 35580 | G197: 44927 | H197: 46022 | I197: 68000 | J197: Marcio Bittencourt | K197: Lateral Direito | L197: 0 | M197: 0 | N197: 300000 | O197: =N197*3.5 -> 1050000 | P197: Direito | Q197: =IF(E197>30,100000,IF(E197>24,120000,IF(E197>16,160000))) -> 120000 | R197: Nike | S197: 1.75 | T197: =TODAY() -> 46296 | U197: =_xlfn.DAYS(H197,T197) -> -274 | V197: =IF(U197<180, "Pre contrato","Com Contrato em vigor") -> Pre contrato | W197: =I197*6 -> 408000 | X197: =I197*13 -> 884000
A198: Yerson Candelo Miranda | B198: Criciúma EC | C198: Criciúma EC | D198: Colômbia | E198: =DATEDIF(F198,TODAY(),"Y") -> 34 | F198: 33658 | G198: 45474 | H198: 46203 | I198: 50000 | J198: Sebastian Olivieri - RPM Foot | K198: Lateral Direito | L198: 0 | M198: 0 | N198: 150000 | O198: =N198*3.5 -> 525000 | P198: Direito | Q198: =IF(E198>30,100000,IF(E198>24,120000,IF(E198>16,160000))) -> 100000 | R198: Adidas | S198: 1.7 | T198: =TODAY() -> 46296 | U198: =_xlfn.DAYS(H198,T198) -> -93 | V198: =IF(U198<180, "Pre contrato","Com Contrato em vigor") -> Pre contrato | W198: =I198*6 -> 300000 | X198: =I198*13 -> 650000
A199: Jonathan Francisco Lemos | B199: Criciúma EC | C199: Criciúma EC | D199: Brasil | E199: =DATEDIF(F199,TODAY(),"Y") -> 34 | F199: 33841 | G199: 45033 | H199: 46022 | I199: 60000 | J199: Sem empresario | K199: Lateral Direito | L199: 0 | M199: 0 | N199: 100000 | O199: =N199*3.5 -> 350000 | P199: Direito | Q199: =IF(E199>30,100000,IF(E199>24,120000,IF(E199>16,160000))) -> 100000 | R199: Adidas | S199: 1.79 | T199: =TODAY() -> 46296 | U199: =_xlfn.DAYS(H199,T199) -> -274 | V199: =IF(U199<180, "Pre contrato","Com Contrato em vigor") -> Pre contrato | W199: =I199*6 -> 360000 | X199: =I199*13 -> 780000
A200: Claudio Coelho Salvático | B200: Criciúma EC | C200: Criciúma EC | D200: Brasil | E200: =DATEDIF(F200,TODAY(),"Y") -> 26 | F200: 36793 | G200: 44291 | H200: 45657 | I200: 60000 | J200: MPX SPORTS | K200: Lateral Direito | L200: 0 | M200: 0 | N200: 120000 | O200: =N200*3.5 -> 420000 | P200: Direito | Q200: =IF(E200>30,100000,IF(E200>24,120000,IF(E200>16,160000))) -> 120000 | R200: Adidas | S200: 1.8 | T200: =TODAY() -> 46296 | U200: =_xlfn.DAYS(H199,T199) -> -274 | V200: =IF(U200<180, "Pre contrato","Com Contrato em vigor") -> Pre contrato | W200: =I200*6 -> 360000 | X200: =I200*13 -> 780000
A201: Patrick de Paula Carneiro | B201: Criciúma EC | C201: Criciúma EC | D201: Brasil | E201: =DATEDIF(F201,TODAY(),"Y") -> 27 | F201: 36411 | G201: 44645 | H201: 46387 | I201: 50000 | J201: Fama Sports | K201: Volante | L201: 0 | M201: 0 | N201: 3000000 | O201: =N201*3.5 -> 10500000 | P201: Esquerdo | Q201: =IF(E201>30,100000,IF(E201>24,120000,IF(E201>16,160000))) -> 120000 | R201: Adidas | S201: 1.8 | T201: =TODAY() -> 46296 | U201: =_xlfn.DAYS(H201,T201) -> 91 | V201: =IF(U201<180, "Pre contrato","Com Contrato em vigor") -> Pre contrato | W201: =I201*6 -> 300000 | X201: =I201*13 -> 650000
A202: Higor Matheus Meritão | B202: Criciúma EC | C202: Criciúma EC | D202: Brasil | E202: =DATEDIF(F202,TODAY(),"Y") -> 32 | F202: 34508 | G202: 44743 | H202: 45657 | I202: 65000 | J202: NG Soccer | K202: Volante | L202: 0 | M202: 0 | N202: 500000 | O202: =N202*3.5 -> 1750000 | P202: Esquerdo | Q202: =IF(E202>30,100000,IF(E202>24,120000,IF(E202>16,160000))) -> 100000 | R202: Adidas | S202: 1.86 | T202: =TODAY() -> 46296 | U202: =_xlfn.DAYS(H202,T202) -> -639 | V202: =IF(U202<180, "Pre contrato","Com Contrato em vigor") -> Pre contrato | W202: =I202*6 -> 390000 | X202: =I202*13 -> 845000
A203: Ronald dos Santos Lopes | B203: Criciúma EC | C203: Criciúma EC | D203: Brasil | E203: =DATEDIF(F203,TODAY(),"Y") -> 29 | F203: 35599 | G203: 45323 | H203: 45657 | I203: 40000 | J203: ADRIANO SPORTS | K203: Volante | L203: 0 | M203: 0 | N203: 500000 | O203: =N203*3.5 -> 1750000 | P203: Direito | Q203: =IF(E203>30,100000,IF(E203>24,120000,IF(E203>16,160000))) -> 120000 | R203: Adidas | S203: 1.71 | T203: =TODAY() -> 46296 | U203: =_xlfn.DAYS(H203,T203) -> -639 | V203: =IF(U203<180, "Pre contrato","Com Contrato em vigor") -> Pre contrato | W203: =I203*6 -> 240000 | X203: =I203*13 -> 520000
A204: Gustavo Bonatto Barreto | B204: Criciúma EC | C204: Criciúma EC | D204: Brasil | E204: =DATEDIF(F204,TODAY(),"Y") -> 30 | F204: 35043 | G204: 45323 | H204: 45991 | I204: 40000 | J204: Marcio Bittencourt | K204: Volante | L204: 0 | M204: 0 | N204: 350000 | O204: =N204*3.5 -> 1225000 | P204: Direito | Q204: =IF(E204>30,100000,IF(E204>24,120000,IF(E204>16,160000))) -> 120000 | R204: Adidas | S204: 1.81 | T204: =TODAY() -> 46296 | U204: =_xlfn.DAYS(H203,T203) -> -639 | V204: =IF(U204<180, "Pre contrato","Com Contrato em vigor") -> Pre contrato | W204: =I204*6 -> 240000 | X204: =I204*13 -> 520000
A205: Mateo Baltasar Barcia Fernández | B205: Criciúma EC | C205: Criciúma EC | D205: Uruguai | E205: =DATEDIF(F205,TODAY(),"Y") -> 25 | F205: 36941 | G205: 44950 | H205: 46022 | I205: 75000 | J205: Scoutfutbol | K205: Volante | L205: 0 | M205: 0 | N205: 350000 | O205: =N205*3.5 -> 1225000 | P205: Direito | Q205: =IF(E205>30,100000,IF(E205>24,120000,IF(E205>16,160000))) -> 120000 | R205: Adidas | S205: 1.82 | T205: =TODAY() -> 46296 | U205: =_xlfn.DAYS(H205,T205) -> -274 | V205: =IF(U205<180, "Pre contrato","Com Contrato em vigor") -> Pre contrato | W205: =I205*6 -> 450000 | X205: =I205*13 -> 975000
A206: Newton Araujo da Costa Júnior | B206: Criciúma EC | C206: Criciúma EC | D206: Brasil | E206: =DATEDIF(F206,TODAY(),"Y") -> 26 | F206: 36597 | G206: 45292 | H206: 46752 | I206: 30000 | J206: Talents Sports | K206: Volante | L206: 0 | M206: 0 | N206: 250000 | O206: =N206*3.5 -> 875000 | P206: Direito | Q206: =IF(E206>30,100000,IF(E206>24,120000,IF(E206>16,160000))) -> 120000 | R206: Adidas | S206: 1.88 | T206: =TODAY() -> 46296 | U206: =_xlfn.DAYS(H206,T206) -> 456 | V206: =IF(U206<180, "Pre contrato","Com Contrato em vigor") -> Com Contrato em vigor | W206: =I206*6 -> 180000 | X206: =I206*13 -> 390000
A207: Matheus Leonardo Sales Cardoso | B207: Criciúma EC | C207: Criciúma EC | D207: Brasil | E207: =DATEDIF(F207,TODAY(),"Y") -> 28 | F207: 35837 | G207: 44950 | H207: 46022 | I207: 30000 | J207: Eleven Soccer | K207: Meio Campo | L207: 0 | M207: 0 | N207: 50000 | O207: =N207*3.5 -> 175000 | P207: Direito | Q207: =IF(E207>30,100000,IF(E207>24,120000,IF(E207>16,160000))) -> 120000 | R207: Adidas | S207: 1.64 | T207: =TODAY() -> 46296 | U207: =_xlfn.DAYS(H207,T207) -> -274 | V207: =IF(U207<180, "Pre contrato","Com Contrato em vigor") -> Pre contrato | W207: =I207*6 -> 180000 | X207: =I207*13 -> 390000
A208: Marcos Gabriel do Nascimento | B208: Criciúma EC | C208: Criciúma EC | D208: Brasil | E208: =DATEDIF(F208,TODAY(),"Y") -> 36 | F208: 33075 | G208: 45292 | H208: 46752 | I208: 150000 | J208: Roc Nation Sports | K208: Meio Campo | L208: 0 | M208: 0 | N208: 80000 | O208: =N208*3.5 -> 280000 | P208: Direito | Q208: =IF(E208>30,100000,IF(E208>24,120000,IF(E208>16,160000))) -> 100000 | R208: Adidas | S208: 1.74 | T208: =TODAY() -> 46296 | U208: =_xlfn.DAYS(H207,T207) -> -274 | V208: =IF(U208<180, "Pre contrato","Com Contrato em vigor") -> Pre contrato | W208: =I208*6 -> 900000 | X208: =I208*13 -> 1950000
A209: Fellipe Mateus de Sena Araujo | B209: Criciúma EC | C209: Criciúma EC | D209: Brasil | E209: =DATEDIF(F209,TODAY(),"Y") -> 35 | F209: 33281 | G209: 44342 | H209: 46022 | I209: 67000 | J209: Sem empresario | K209: Meio Campo | L209: 0 | M209: 0 | N209: 200000 | O209: =N209*3.5 -> 700000 | P209: Direito | Q209: =IF(E209>30,100000,IF(E209>24,120000,IF(E209>16,160000))) -> 100000 | R209: Adidas | S209: 1.78 | T209: =TODAY() -> 46296 | U209: =_xlfn.DAYS(H209,T209) -> -274 | V209: =IF(U209<180, "Pre contrato","Com Contrato em vigor") -> Pre contrato | W209: =I209*6 -> 402000 | X209: =I209*13 -> 871000
A210: Pedro Rocha Neves | B210: Criciúma EC | C210: Criciúma EC | D210: Brasil | E210: =DATEDIF(F210,TODAY(),"Y") -> 32 | F210: 34608 | G210: 45323 | H210: 45657 | I210: 100000 | J210: HWS GRUPO | K210: Atacante | L210: 1 | M210: 12 | N210: 1500000 | O210: =N210*3.5 -> 5250000 | P210: Esquerdo | Q210: =IF(E210>30,100000,IF(E210>24,120000,IF(E210>16,160000))) -> 100000 | R210: Adidas | S210: 1.75 | T210: =TODAY() -> 46296 | U210: =_xlfn.DAYS(H210,T210) -> -639 | V210: =IF(U210<180, "Pre contrato","Com Contrato em vigor") -> Pre contrato | W210: =I210*6 -> 600000 | X210: =I210*13 -> 1300000
A211: Sérgio Antonio da Luz Junior | B211: Criciúma EC | C211: Criciúma EC | D211: Brasil | E211: =DATEDIF(F211,TODAY(),"Y") -> 31 | F211: 34795 | G211: 45108 | H211: 46022 | I211: 50000 | J211: Granja Sports | K211: Atacante | L211: 0 | M211: 0 | N211: 160000 | O211: =N211*3.5 -> 560000 | P211: Direito | Q211: =IF(E211>30,100000,IF(E211>24,120000,IF(E211>16,160000))) -> 100000 | R211: Adidas | S211: 1.8 | T211: =TODAY() -> 46296 | U211: =_xlfn.DAYS(H211,T211) -> -274 | V211: =IF(U211<180, "Pre contrato","Com Contrato em vigor") -> Pre contrato | W211: =I211*6 -> 300000 | X211: =I211*13 -> 650000
A212: Arthur Caíke do Nascimento Cruz | B212: Criciúma EC | C212: Criciúma EC | D212: Brasil | E212: =DATEDIF(F212,TODAY(),"Y") -> 34 | F212: 33770 | G212: 45323 | H212: 45657 | I212: 76000 | J212: REC Sports | K212: Atacante | L212: 2 | M212: 21 | N212: 350000 | O212: =N212*3.5 -> 1225000 | P212: Direito | Q212: =IF(E212>30,100000,IF(E212>24,120000,IF(E212>16,160000))) -> 100000 | R212: Adidas | S212: 1.74 | T212: =TODAY() -> 46296 | U212: =_xlfn.DAYS(H211,T211) -> -274 | V212: =IF(U212<180, "Pre contrato","Com Contrato em vigor") -> Pre contrato | W212: =I212*6 -> 456000 | X212: =I212*13 -> 988000
A213: Yannick Bolasie | B213: Criciúma EC | C213: Criciúma EC | D213: Inglaterra | E213: =DATEDIF(F213,TODAY(),"Y") -> 37 | F213: 32652 | G213: 45323 | H213: 45657 | I213: 150000 | J213: S.S.G | K213: Atacante | L213: 0 | M213: 0 | N213: 1000000 | O213: =N213*3.5 -> 3500000 | P213: Direito | Q213: =IF(E213>30,100000,IF(E213>24,120000,IF(E213>16,160000))) -> 100000 | R213: Adidas | S213: 1.85 | T213: =TODAY() -> 46296 | U213: =_xlfn.DAYS(H213,T213) -> -639 | V213: =IF(U213<180, "Pre contrato","Com Contrato em vigor") -> Pre contrato | W213: =I213*6 -> 900000 | X213: =I213*13 -> 1950000
A214: Eduardo de Queiroz Melo | B214: Criciúma EC | C214: Criciúma EC | D214: Brasil | E214: =DATEDIF(F214,TODAY(),"Y") -> 25 | F214: 37024 | G214: 44256 | H214: 46022 | I214: 30000 | J214: Ferreira Sports | K214: Atacante | L214: 0 | M214: 0 | N214: 100000 | O214: =N214*3.5 -> 350000 | P214: Direito | Q214: =IF(E214>30,100000,IF(E214>24,120000,IF(E214>16,160000))) -> 120000 | R214: Adidas | S214: 1.85 | T214: =TODAY() -> 46296 | U214: =_xlfn.DAYS(H214,T214) -> -274 | V214: =IF(U214<180, "Pre contrato","Com Contrato em vigor") -> Pre contrato | W214: =I214*6 -> 180000 | X214: =I214*13 -> 390000
...

Sheet Clube
A1: Clube | B1: Estado | C1: Pay Per View | D1: Receita de TV | E1: Salario dos jogadores mensal | F1: Salario dos jogadores anual | G1: Torcida no estado | H1: Estadio mandante | I1: Socio torcedor | J1: Capacidade do estadio | K1: Preco medio dos ingressos do estadio | L1: media de publico por jogo no estadio | M1: Média de renda por jogo | N1: Renda total no estadio | O1: Projeção de Venda de Atletas
A2: Athletico Paranaense | B2: PA | C2: 0 | D2: 10 | E2: =SUMIF(Atletas!B:B, A2, Atletas!I:I) -> 11148000 | F2: =SUMIF(Atletas!B:B, A2, Atletas!X:X) -> 144924000 | G2: 1.5 | H2: Ligga Arena | I2: 40000 | J2: 42372 | K2: 35.63 | L2: 28310 | M2: 1007365.4 | N2: 34250425 | O2: =100 * 1000000 -> 100000000
A3: Atlético Goianiense | B3: GO | C3: 0 | D3: 10 | E3: =SUMIF(Atletas!B:B, A3, Atletas!I:I) -> 1001267 | F3: =SUMIF(Atletas!B:B, A3, Atletas!X:X) -> 13016471 | G3: 0.2 | H3: Estádio Antonio Accioly | I3: 7294 | J3: 13000 | K3: 55.25 | L3: 6462 | M3: 357038.5 | N3: 10711155 | O3: =5 * 1000000 -> 5000000
A4: Criciúma EC | B4: SC | C4: 0 | D4: 10 | E4: =SUMIF(Atletas!B:B, A4, Atletas!I:I) -> 2056000 | F4: =SUMIF(Atletas!B:B, A4, Atletas!X:X) -> 26728000 | G4: 0.2 | H4: Estádio Heriberto Hülse | I4: 16000 | J4: 19225 | K4: 38.32 | L4: 12748 | M4: 488511 | N4: 14655330 | O4: =5* 1000000 -> 5000000
A5: Cuiabá EC | B5: MS | C5: 0 | D5: 15 | E5: =SUMIF(Atletas!B:B, A5, Atletas!I:I) -> 4684000 | F5: =SUMIF(Atletas!B:B, A5, Atletas!X:X) -> 60892000 | G5: 0.4 | H5: Arena Pantanal | I5: 3000 | J5: 42968 | K5: 63.38 | L5: 7572 | M5: 267247.06 | N5: 9086400 | O5: =5* 1000000 -> 5000000
A6: EC Juventude | B6: RS | C6: 0 | D6: 10 | E6: =SUMIF(Atletas!B:B, A6, Atletas!I:I) -> 2105000 | F6: =SUMIF(Atletas!B:B, A6, Atletas!X:X) -> 27365000 | G6: 0.2 | H6: Estádio Alfredo Jaconi | I6: 8380 | J6: 23726 | K6: 50.58 | L6: 8654 | M6: 437704.23 | N6: 13131127 | O6: =10 * 1000000 -> 10000000
A7: EC Vitória | B7: BA | C7: 0 | D7: 10 | E7: =SUMIF(Atletas!B:B, A7, Atletas!I:I) -> 5575000 | F7: =SUMIF(Atletas!B:B, A7, Atletas!X:X) -> 72475000 | G7: 3.9 | H7: Estádio Manoel Barradas | I7: 40638 | J7: 30618 | K7: 26.88 | L7: 20391 | M7: 548119.4 | N7: 16443582 | O7: =15* 1000000 -> 15000000
A8: RB Bragantino | B8: SP | C8: 0 | D8: 10 | E8: =SUMIF(Atletas!B:B, A8, Atletas!I:I) -> 13474000 | F8: =SUMIF(Atletas!B:B, A8, Atletas!X:X) -> 175162000 | G8: 0.2 | H8: Estádio Nabi Abi Chedid | I8: 7500 | J8: 15010 | K8: 43.84 | L8: 5987 | M8: 243104.14 | N8: 8508645 | O8: =40* 1000000 -> 40000000
A9: CR Flamengo | B9: RJ | C9: 177 | D9: 25 | E9: =SUMIF(Atletas!B:B, A9, Atletas!I:I) -> 24280000 | F9: =SUMIF(Atletas!B:B, A9, Atletas!X:X) -> 315640000 | G9: 43.2 | H9: Estádio Jornalista Mário Filho | I9: 77577 | J9: 78838 | K9: 68.06 | L9: 51644 | M9: 3514821.7 | N9: 130048403 | O9: =103 * 1000000 -> 103000000
A10: SC Corinthians | B10: SP | C10: 118 | D10: 19 | E10: =SUMIF(Atletas!B:B, A10, Atletas!I:I) -> 20170000 | F10: =SUMIF(Atletas!B:B, A10, Atletas!X:X) -> 262210000 | G10: 31.1 | H10: Neo Química Arena | I10: 43000 | J10: 49205 | K10: 57.32 | L10: 42693 | M10: 2446942.5 | N10: 85642986 | O10: =180 * 1000000 -> 180000000
A11: Grêmio FBPA | B11: RS | C11: 57 | D11: 36 | E11: =SUMIF(Atletas!B:B, A11, Atletas!I:I) -> 15400000 | F11: =SUMIF(Atletas!B:B, A11, Atletas!X:X) -> 200200000 | G11: 9.9 | H11: Arena do Grêmio | I11: 98153 | J11: 60540 | K11: 61.38 | L11: 22002 | M11: 1350509.5 | N11: 45917324 | O11: =90 * 1000000 -> 90000000
A12: SE Palmeiras | B12: SP | C12: 50 | D12: 33 | E12: =SUMIF(Atletas!B:B, A12, Atletas!I:I) -> 15880000 | F12: =SUMIF(Atletas!B:B, A12, Atletas!X:X) -> 206440000 | G12: 16.3 | H12: Allianz Parque | I12: 197327 | J12: 43713 | K12: 83.91 | L12: 30490 | M12: 2558529.9 | N12: 86990017 | O12: =295.1 * 1000000 -> 295100000
A13: São Paulo FC | B13: SP | C13: 28 | D13: 31 | E13: =SUMIF(Atletas!B:B, A13, Atletas!I:I) -> 13316000 | F13: =SUMIF(Atletas!B:B, A13, Atletas!X:X) -> 173108000 | G13: 15.6 | H13: MorumBIS | I13: 57106 | J13: 66795 | K13: 65.49 | L13: 44088 | M13: 2887163.8 | N13: 98163569 | O13: =174.1* 1000000 -> 174100000
A14: CR Vasco da Gama | B14: RJ | C14: 21 | D14: 29 | E14: =SUMIF(Atletas!B:B, A14, Atletas!I:I) -> 11863000 | F14: =SUMIF(Atletas!B:B, A14, Atletas!X:X) -> 154219000 | G14: 14.1 | H14: Estádio São Januário | I14: 62153 | J14: 24584 | K14: 64.91 | L14: 21686 | M14: 1407571.9 | N14: 43634730 | O14: =70* 1000000 -> 70000000
A15: Cruzeiro EC | B15: MG | C15: 18 | D15: 32 | E15: =SUMIF(Atletas!B:B, A15, Atletas!I:I) -> 16052000 | F15: =SUMIF(Atletas!B:B, A15, Atletas!X:X) -> 208676000 | G15: 11.6 | H15: Estádio Governador Magalhães Pinto | I15: 81004 | J15: 61927 | K15: 53.34 | L15: 32890 | M15: 1754414.7 | N15: 52632441 | O15: =80* 1000000 -> 80000000
A16: Atlético Mineiro | B16: MG | C16: 16 | D16: 30 | E16: =SUMIF(Atletas!B:B, A16, Atletas!I:I) -> 12742222 | F16: =SUMIF(Atletas!B:B, A16, Atletas!X:X) -> 165648886 | G16: 8.6 | H16: Arena MRV | I16: 113169 | J16: 46000 | K16: 76.16 | L16: 31962 | M16: 2434137.2 | N16: 80326527 | O16: =60* 1000000 -> 60000000
A17: SC Internacional | B17: RS | C17: 16 | D17: 30 | E17: =SUMIF(Atletas!B:B, A17, Atletas!I:I) -> 17425000 | F17: =SUMIF(Atletas!B:B, A17, Atletas!X:X) -> 226525000 | G17: 6.2 | H17: Estádio Beira-Rio | I17: 107265 | J17: 50848 | K17: 42.82 | L17: 29526 | M17: 1264198.9 | N17: 37925967 | O17: =135* 1000000 -> 135000000
A18: Botafogo FR | B18: RJ | C18: 15 | D18: 33 | E18: =SUMIF(Atletas!B:B, A18, Atletas!I:I) -> 23012000 | F18: =SUMIF(Atletas!B:B, A18, Atletas!X:X) -> 299156000 | G18: 6.2 | H18: Estádio Olímpico Nilton Santos | I18: 80977 | J18: 46931 | K18: 63.08 | L18: 22467 | M18: 1417292 | N18: 52439805 | O18: =100* 1000000 -> 100000000
A19: Fluminense FC | B19: RJ | C19: 11 | D19: 30 | E19: =SUMIF(Atletas!B:B, A19, Atletas!I:I) -> 18175000 | F19: =SUMIF(Atletas!B:B, A19, Atletas!X:X) -> 236275000 | G19: 6 | H19: Estádio Jornalista Mário Filho | I19: 49950 | J19: 78838 | K19: 47.08 | L19: 31699 | M19: 1492477.2 | N19: 50744226 | O19: =80* 1000000 -> 80000000
A20: EC Bahia | B20: BA | C20: 5 | D20: 18 | E20: =SUMIF(Atletas!B:B, A20, Atletas!I:I) -> 15422152 | F20: =SUMIF(Atletas!B:B, A20, Atletas!X:X) -> 200487976 | G20: 6 | H20: Arena Fonte Nova | I20: 75000 | J20: 47364 | K20: 33.88 | L20: 34214 | M20: 1159180.9 | N20: 40571331 | O20: =50* 1000000 -> 50000000
A21: Fortaleza EC | B21: CE | C21: 5 | D21: 13 | E21: =SUMIF(Atletas!B:B, A21, Atletas!I:I) -> 7563000 | F21: =SUMIF(Atletas!B:B, A21, Atletas!X:X) -> 98319000 | G21: 3.4 | H21: Estádio Governador Plácido Castelo | I21: 43860 | J21: 60326 | K21: 21.29 | L21: 30221 | M21: 643266.73 | N21: 23800869 | O21: =40* 1000000 -> 40000000
